geosoup/__init__.py
geosoup/common.py
geosoup/exceptions.py
geosoup/raster.py
geosoup/terrain.py
geosoup/vector.py
geosoup-0.1.82.dist-info/LICENSE
geosoup-0.1.82.dist-info/METADATA
geosoup-0.1.82.dist-info/WHEEL
geosoup-0.1.82.dist-info/top_level.txt
geosoup-0.1.82.dist-info/RECORD
